krules_fastapi_env/__init__.py
krules_fastapi_env/app.py
krules_fastapi_env/globals.py
krules_fastapi_env-0.12.1.dist-info/AUTHORS
krules_fastapi_env-0.12.1.dist-info/LICENSE
krules_fastapi_env-0.12.1.dist-info/METADATA
krules_fastapi_env-0.12.1.dist-info/WHEEL
krules_fastapi_env-0.12.1.dist-info/RECORD
